enflow/__init__.py
enflow/base.py
enflow/assets/__init__.py
enflow/assets/abstract.py
enflow/assets/base.py
enflow/assets/battery.py
enflow/assets/building.py
enflow/assets/energycollection.py
enflow/assets/geospatial.py
enflow/assets/heatpump.py
enflow/assets/hydro.py
enflow/assets/powergrid.py
enflow/assets/solar.py
enflow/assets/timeseries.py
enflow/assets/wind.py
enflow/examples/__init__.py
enflow/examples/building.py
enflow/examples/microgrid.py
enflow/examples/gefcom2014_solar/__init__.py
enflow/examples/gefcom2014_solar/main.py
enflow/models/__init__.py
enflow/models/agent.py
enflow/models/optimizer.py
enflow/models/predictor.py
enflow/models/simulator.py
enflow/problems/__init__.py
enflow/problems/check.py
enflow/problems/dataset.py
enflow/problems/environment.py
enflow/problems/objective.py
enflow/problems/problem.py
enflow/spaces/__init__.py
enflow/spaces/base.py
enflow/spaces/dataframe.py
enflow/spaces/input.py
enflow/spaces/output.py
enflow-0.0.3.post1.dist-info/licenses/LICENCE.md
enflow-0.0.3.post1.dist-info/METADATA
enflow-0.0.3.post1.dist-info/WHEEL
enflow-0.0.3.post1.dist-info/top_level.txt
enflow-0.0.3.post1.dist-info/RECORD
