Metadata-Version: 2.4
Name: enflow
Version: 0.0.3.post1
Summary: ⚡ Open-source framework for sequential decision problems in the energy sector
Author: rebase.energy
License: MIT
Project-URL: homepage, https://enflow.org
Project-URL: repository, https://github.com/rebase-energy/enflow
Project-URL: documentation, https://docs.enflow.org/en/latest
Requires-Python: >=3.11
License-File: LICENCE.md
Requires-Dist: build>=1.2.2
Requires-Dist: energydatamodel>=0.0.2
Requires-Dist: gymnasium>=1.1.1
Requires-Dist: myst-parser>=4.0.1
Requires-Dist: twine>=6.1.0
Provides-Extra: dev
Requires-Dist: ipykernel>=6.29.5; extra == "dev"
Requires-Dist: ipywidgets>=8.1.5; extra == "dev"
Requires-Dist: nbsphinx>=0.9.7; extra == "dev"
Requires-Dist: sphinx==7.2.6; extra == "dev"
Requires-Dist: sphinx-autodoc-typehints>=2.0.1; extra == "dev"
Requires-Dist: sphinx-rtd-theme>=3.0.2; extra == "dev"
Dynamic: license-file
